ipadumper/__init__.py
ipadumper/__main__.py
ipadumper/appledl.py
ipadumper/controller.py
ipadumper/dump.js
ipadumper/main.py
ipadumper/utils.py
ipadumper/appstore_images/dark/cloud.png
ipadumper/appstore_images/dark/de/dissallow.png
ipadumper/appstore_images/dark/de/get.png
ipadumper/appstore_images/dark/de/install.png
ipadumper/appstore_images/dark/en/dissallow.png
ipadumper/appstore_images/dark/en/get.png
ipadumper/appstore_images/dark/en/install.png
ipadumper/appstore_images/light/cloud.png
ipadumper/appstore_images/light/de/dissallow.png
ipadumper/appstore_images/light/de/get.png
ipadumper/appstore_images/light/de/install.png
ipadumper/appstore_images/light/en/dissallow.png
ipadumper/appstore_images/light/en/get.png
ipadumper/appstore_images/light/en/install.png
ipadumper-0.0.14.dist-info/LICENSE.md
ipadumper-0.0.14.dist-info/METADATA
ipadumper-0.0.14.dist-info/WHEEL
ipadumper-0.0.14.dist-info/entry_points.txt
ipadumper-0.0.14.dist-info/top_level.txt
ipadumper-0.0.14.dist-info/RECORD
