Metadata-Version: 2.1
Name: ipadumper
Version: 0.0.14
Summary: Automatically install apps on a jailbroken device iOS device and generate decrypted IPAs
Home-page: https://gitlab.com/marzzzello/ipa-dumper
Author: marzzzello
Author-email: ipa_dumper@07f.de
License: UNKNOWN
Project-URL: Bug Tracker, https://gitlab.com/marzzzello/ipa-dumper/issues
Platform: UNKNOWN
Classifier: Programming Language :: Python :: 3
Classifier: License :: OSI Approved :: MIT License
Requires-Python: >=3.7
License-File: LICENSE.md
Requires-Dist: cachetools
Requires-Dist: coloredlogs
Requires-Dist: commentjson
Requires-Dist: frida
Requires-Dist: paramiko
Requires-Dist: scp
Requires-Dist: tqdm
Requires-Dist: zxtouch
